{
  "editor:focus-right": [
    {
      "modifiers": [
        "Mod"
      ],
      "key": "L"
    }
  ],
  "editor:focus-left": [
    {
      "modifiers": [
        "Mod"
      ],
      "key": "H"
    }
  ],
  "editor:open-search-replace": [
    {
      "modifiers": [
        "Mod",
        "Shift"
      ],
      "key": "F"
    }
  ],
  "editor:toggle-checklist-status": [
    {
      "modifiers": [
        "Mod",
        "Shift"
      ],
      "key": "L"
    }
  ],
  "app:toggle-left-sidebar": [
    {
      "modifiers": [
        "Mod"
      ],
      "key": "E"
    }
  ],
  "app:toggle-right-sidebar": [
    {
      "modifiers": [
        "Mod",
        "Shift"
      ],
      "key": "E"
    }
  ],
  "markdown:toggle-preview": [
    {
      "modifiers": [
        "Mod"
      ],
      "key": "\\"
    }
  ],
  "switcher:open": [
    {
      "modifiers": [
        "Mod"
      ],
      "key": "K"
    }
  ],
  "obsidian-excalidraw-plugin:save": [],
  "auto-card-link:auto-card-link-enhance-selected-url": [],
  "auto-card-link:auto-card-link-paste-and-enhance": [
    {
      "modifiers": [
        "Mod",
        "Shift"
      ],
      "key": "V"
    }
  ],
  "app:delete-file": [
    {
      "modifiers": [
        "Alt"
      ],
      "key": "Delete"
    }
  ],
  "editor:toggle-source": [
    {
      "modifiers": [
        "Mod",
        "Shift"
      ],
      "key": "\\"
    }
  ],
  "file-explorer:move-file": [
    {
      "modifiers": [
        "Mod"
      ],
      "key": "M"
    }
  ],
  "copilot:chat-toggle-window": [
    {
      "modifiers": [
        "Mod",
        "Shift"
      ],
      "key": "I"
    }
  ],
  "markdown:add-metadata-property": [],
  "editor:add-cursor-below": [
    {
      "modifiers": [
        "Alt",
        "Mod"
      ],
      "key": "J"
    }
  ],
  "editor:add-cursor-above": [
    {
      "modifiers": [
        "Alt",
        "Mod"
      ],
      "key": "K"
    }
  ],
  "editor:delete-paragraph": [],
  "graph:open": [],
  "obsidian-icon-folder:iconize:set-icon-for-file": [],
  "editor:insert-link": [],
  "app:open-help": [],
  "global-search:open": [
    {
      "modifiers": [
        "Mod",
        "Shift"
      ],
      "key": "S"
    }
  ],
  "editor:toggle-code": [
    {
      "modifiers": [
        "Mod"
      ],
      "key": ";"
    }
  ],
  "editor:set-heading": [
    {
      "modifiers": [
        "Mod",
        "Shift"
      ],
      "key": "3"
    }
  ],
  "editor:toggle-bullet-list": [
    {
      "modifiers": [
        "Alt"
      ],
      "key": "-"
    }
  ],
  "workspace:export-pdf": [
    {
      "modifiers": [
        "Mod",
        "Shift"
      ],
      "key": "P"
    }
  ],
  "templater-obsidian:insert-templater": [
    {
      "modifiers": [
        "Alt"
      ],
      "key": "T"
    }
  ],
  "file-explorer:open": [
    {
      "modifiers": [
        "Alt"
      ],
      "key": "E"
    }
  ]
}